README.md
setup.py
samutils/__init__.py
samutils.egg-info/PKG-INFO
samutils.egg-info/SOURCES.txt
samutils.egg-info/dependency_links.txt
samutils.egg-info/requires.txt
samutils.egg-info/top_level.txt
samutils/util/__init__.py
samutils/util/assisttool.py
samutils/util/commonwrapper.py
samutils/util/complexutil.py
samutils/util/esutil.py
samutils/util/fileutil.py
samutils/util/logutil.py
samutils/util/mysqlutil.py
samutils/util/pdutil.py
samutils/util/strutil.py