Metadata-Version: 2.1
Name: samutils
Version: 0.0.0.3
Summary: mysql file elasticsearch utils
Home-page: https://gitee.com/sanmubird/sam_utils
Author: sam
Author-email: sanmubird@qq.com
License: UNKNOWN
Keywords: mysql,file,elasticsearch
Platform: UNKNOWN
Requires-Python: >=3
